QgisJiaochengRumenYuJinjie/README.md
QgisJiaochengRumenYuJinjie/__init__.py
QgisJiaochengRumenYuJinjie/__main__.py
QgisJiaochengRumenYuJinjie/file.epub
QgisJiaochengRumenYuJinjie/index.html
QgisJiaochengRumenYuJinjie/css/__init__.py
QgisJiaochengRumenYuJinjie/css/annotations.css
QgisJiaochengRumenYuJinjie/css/main.css
QgisJiaochengRumenYuJinjie/css/normalize.css
QgisJiaochengRumenYuJinjie/css/popup.css
QgisJiaochengRumenYuJinjie/font/__init__.py
QgisJiaochengRumenYuJinjie/font/fontello.eot
QgisJiaochengRumenYuJinjie/font/fontello.svg
QgisJiaochengRumenYuJinjie/font/fontello.ttf
QgisJiaochengRumenYuJinjie/font/fontello.woff
QgisJiaochengRumenYuJinjie/img/__init__.py
QgisJiaochengRumenYuJinjie/img/annotator-glyph-sprite.png
QgisJiaochengRumenYuJinjie/img/annotator-icon-sprite.png
QgisJiaochengRumenYuJinjie/img/apple-touch-icon.png
QgisJiaochengRumenYuJinjie/img/cancelfullscreen.png
QgisJiaochengRumenYuJinjie/img/close.png
QgisJiaochengRumenYuJinjie/img/fullscreen.png
QgisJiaochengRumenYuJinjie/img/loader.gif
QgisJiaochengRumenYuJinjie/img/menu-icon.png
QgisJiaochengRumenYuJinjie/img/save.png
QgisJiaochengRumenYuJinjie/img/saved.png
QgisJiaochengRumenYuJinjie/img/settings-s.png
QgisJiaochengRumenYuJinjie/img/settings.png
QgisJiaochengRumenYuJinjie/img/star.png
QgisJiaochengRumenYuJinjie/js/__init__.py
QgisJiaochengRumenYuJinjie/js/epub.js
QgisJiaochengRumenYuJinjie/js/epub.min.js
QgisJiaochengRumenYuJinjie/js/epub.min.map
QgisJiaochengRumenYuJinjie/js/hooks.min.js
QgisJiaochengRumenYuJinjie/js/hooks.min.map
QgisJiaochengRumenYuJinjie/js/reader.js
QgisJiaochengRumenYuJinjie/js/reader.js.map
QgisJiaochengRumenYuJinjie/js/reader.min.js
QgisJiaochengRumenYuJinjie/js/reader.min.map
QgisJiaochengRumenYuJinjie/js/hooks/__init__.py
QgisJiaochengRumenYuJinjie/js/hooks/extensions/__init__.py
QgisJiaochengRumenYuJinjie/js/hooks/extensions/highlight.js
QgisJiaochengRumenYuJinjie/js/libs/__init__.py
QgisJiaochengRumenYuJinjie/js/libs/jquery.min.js
qgis_jiaocheng_rumen_yu_jinjie-2024.3.5.0.dist-info/METADATA
qgis_jiaocheng_rumen_yu_jinjie-2024.3.5.0.dist-info/WHEEL
qgis_jiaocheng_rumen_yu_jinjie-2024.3.5.0.dist-info/entry_points.txt
qgis_jiaocheng_rumen_yu_jinjie-2024.3.5.0.dist-info/top_level.txt
qgis_jiaocheng_rumen_yu_jinjie-2024.3.5.0.dist-info/RECORD
